autoencodersplz/__init__.py
autoencodersplz/backbones/__init__.py
autoencodersplz/backbones/mlp.py
autoencodersplz/backbones/mlp_mixer.py
autoencodersplz/backbones/resnet.py
autoencodersplz/backbones/vision_transformer.py
autoencodersplz/layers/__init__.py
autoencodersplz/layers/dimensions.py
autoencodersplz/layers/patch_embed.py
autoencodersplz/layers/vector_quantize.py
autoencodersplz/models/__init__.py
autoencodersplz/models/fsqvae.py
autoencodersplz/models/i_jepa.py
autoencodersplz/models/mae.py
autoencodersplz/models/maemix.py
autoencodersplz/models/mlp_ae.py
autoencodersplz/models/mlp_residual_ae.py
autoencodersplz/models/residual_ae.py
autoencodersplz/models/vqvae.py
autoencodersplz/trainers/__init__.py
autoencodersplz/trainers/basic.py
autoencodersplz/trainers/loaders.py
autoencodersplz/trainers/loggers.py
autoencodersplz/trainers/schedulers.py
autoencodersplz-2024.2.8.dist-info/METADATA
autoencodersplz-2024.2.8.dist-info/WHEEL
autoencodersplz-2024.2.8.dist-info/licenses/LICENSE
autoencodersplz-2024.2.8.dist-info/RECORD
