Metadata-Version: 2.1
Name: autoencodersplz
Version: 2024.2.8
Summary: Generative modeling and representation learning through reconstruction
Project-URL: Homepage, https://github.com/tomouellette/autoencodersplz
Project-URL: Issues, https://github.com/tomouellette/autoencodersplz/issues
Author: Tom W. Ouellette, Yiran Shao
License-File: LICENSE
Classifier: License :: OSI Approved :: MIT License
Classifier: Operating System :: OS Independent
Classifier: Programming Language :: Python :: 3
Requires-Python: >=3.7
